pycmd/__init__.py
pycmd/__main__.py
pycmd/commands/create.py
pycmd/commands/help.py
pycmd/commands/ls.py
pycmd/commands/open.py
pycmd/commands/rm.py
pycmd/commands/setup.py
pycmd/commands/src.py
pycmd/json/commands.json
pycmd/utils/pycmd.py
pycmd_cli-4.0.3.dist-info/LICENSE
pycmd_cli-4.0.3.dist-info/METADATA
pycmd_cli-4.0.3.dist-info/WHEEL
pycmd_cli-4.0.3.dist-info/entry_points.txt
pycmd_cli-4.0.3.dist-info/top_level.txt
pycmd_cli-4.0.3.dist-info/RECORD
