Metadata-Version: 2.1
Name: pycmd-cli
Version: 4.0.3
Summary: PyCmd is a command-line tool to help you manage your projects.
License: MIT
Keywords: pycmd-cli,pycmd
Requires-Python: >=3.6
License-File: LICENSE
Requires-Dist: colorama (>=0.4.4)
Requires-Dist: cursor (>=1.3.4)
Requires-Dist: inquirer (>=2.9.1)
Requires-Dist: PyGithub (>=1.55)
Requires-Dist: python-dotenv (>=0.19.2)
Requires-Dist: requests (>=2.26.0)
Requires-Dist: setuptools (>=58.1.0)
Requires-Dist: getch (>=1.0)
